asynchat/__init__.py
asynchat/asynchat.py
pyasynchat-1.0.3.dist-info/LICENSE
pyasynchat-1.0.3.dist-info/METADATA
pyasynchat-1.0.3.dist-info/WHEEL
pyasynchat-1.0.3.dist-info/top_level.txt
pyasynchat-1.0.3.dist-info/RECORD
