Metadata-Version: 2.1
Name: pyasynchat
Version: 1.0.3
Summary: Make asynchat available for Python 3.12 onwards
Home-page: https://github.com/simonrob/pyasynchat
Author: Simon Robinson
Author-email: simon@robinson.ac
License: Python Software Foundation License Version 2
Platform: any
Classifier: Development Status :: 5 - Production/Stable
Classifier: License :: OSI Approved :: Python Software Foundation License
Classifier: Programming Language :: Python :: 3.12
Classifier: Programming Language :: Python :: 3.13
License-File: LICENSE
Requires-Dist: pyasyncore >=1.0.2
